log_ip/__init__.py
log_ip/log_ip.py
log_ip-0.0.2.dist-info/LICENSE
log_ip-0.0.2.dist-info/METADATA
log_ip-0.0.2.dist-info/WHEEL
log_ip-0.0.2.dist-info/entry_points.txt
log_ip-0.0.2.dist-info/top_level.txt
log_ip-0.0.2.dist-info/RECORD
