Metadata-Version: 2.1
Name: log-ip
Version: 0.0.2
Summary: A script that dumps your IP into a log file
Home-page: https://github.com/FrenchCommando/log_ip
Author: FrenchCommando
Author-email: martialren@gmail.com
License: UNKNOWN
Platform: UNKNOWN
Classifier: Programming Language :: Python :: 3.7
Classifier: License :: OSI Approved :: MIT License
Classifier: Operating System :: OS Independent
